puyu/__init__.py
puyu/puyu.py
puyu/py.typed
puyu-0.0.1a0.dist-info/WHEEL
puyu-0.0.1a0.dist-info/METADATA
puyu-0.0.1a0.dist-info/RECORD
